MinDAEC/__init__.py
mindaec-0.1.0.dist-info/METADATA
mindaec-0.1.0.dist-info/WHEEL
mindaec-0.1.0.dist-info/top_level.txt
mindaec-0.1.0.dist-info/RECORD
